Metadata-Version: 2.1
Name: fca-lazy-clf
Version: 0.3
Summary: Lazy binary classifier based on Formal Concept Analysis
Home-page: https://github.com/vpozdnyakov/fca_lazy_clf
Author: Vitaliy Pozdnyakov
Author-email: pozdnyakov.vitaliy@yandex.ru
License: MIT
Keywords: fca,formal-concept-analysis,lazy-learning,binary-classification
Platform: UNKNOWN
Classifier: Development Status :: 3 - Alpha
Classifier: Intended Audience :: Developers
Classifier: License :: OSI Approved :: MIT License
Classifier: Programming Language :: Python :: 3
